elrahdjango/__init__.py
elrahdjango/utilty/__init__.py
elrahdjango/utilty/functions.py
elrahdjango/validators/__init__.py
elrahdjango/validators/files.py
elrahdjango/validators/password.py
elrahdjango/views/__init__.py
elrahdjango/views/auth.py
elrahdjango-0.0.2.dist-info/METADATA
elrahdjango-0.0.2.dist-info/WHEEL
elrahdjango-0.0.2.dist-info/top_level.txt
elrahdjango-0.0.2.dist-info/RECORD
