Metadata-Version: 2.4
Name: elrahdjango
Version: 0.0.2
Summary: Package personnalisé pour optimiser le développement avec django
Home-page: https://github.com/Harlequelrah/Library-ElrahDjango
Author: Harlequelrah
Author-email: maximeatsoudegbovi@example.com
Maintainer: jordanBuilder
Maintainer-email: tomegahjordan81@gmail.com
License: LGPL-3.0-only
Requires-Python: >=3.10
Requires-Dist: django>=5.2
Dynamic: author
Dynamic: author-email
Dynamic: description
Dynamic: description-content-type
Dynamic: home-page
Dynamic: license
Dynamic: maintainer
Dynamic: maintainer-email
Dynamic: requires-dist
Dynamic: requires-python
Dynamic: summary
